pylandsat/__init__.py
pylandsat/bands.json
pylandsat/catalog.py
pylandsat/cli.py
pylandsat/database.py
pylandsat/download.py
pylandsat/files.json
pylandsat/preprocessing.py
pylandsat/queries.py
pylandsat/scene.py
pylandsat/utils.py
pylandsat-0.6.0.dist-info/entry_points.txt
pylandsat-0.6.0.dist-info/LICENSE.txt
pylandsat-0.6.0.dist-info/WHEEL
pylandsat-0.6.0.dist-info/METADATA
pylandsat-0.6.0.dist-info/RECORD
