Metadata-Version: 2.1
Name: pylandsat
Version: 0.6.0
Summary: Search, download and preprocess Landsat imagery
Home-page: https://github.com/yannforget/pylandsat
License: MIT
Keywords: earth observation,remote sesing,GIS,satellite imagery,landsat
Author: Yann Forget
Author-email: yannforget@mailbox.org
Maintainer: Yann Forget
Maintainer-email: yannforget@mailbox.org
Requires-Python: >=3.6,<4.0
Classifier: License :: OSI Approved :: MIT License
Classifier: Programming Language :: Python :: 3
Classifier: Programming Language :: Python :: 3.6
Classifier: Programming Language :: Python :: 3.7
Classifier: Programming Language :: Python :: 3.8
Classifier: Programming Language :: Python :: 3.9
Requires-Dist: appdirs
Requires-Dist: click
Requires-Dist: fiona
Requires-Dist: geopy
Requires-Dist: numpy
Requires-Dist: python-dateutil
Requires-Dist: rasterio (>=1.0,<2.0)
Requires-Dist: requests (>=2.20,<3.0)
Requires-Dist: shapely
Requires-Dist: tqdm
Project-URL: Documentation, https://github.com/yannforget/pylandsat
Project-URL: Repository, https://github.com/yannforget/pylandsat
